Workbook

Sheet Raw Financials
A1: Fiscal Year | B1: 2025 | C1: 2024 | D1: 2023
A3: Income Statement
A4: Net Sales | B4: 2558730 | C4: 2457091 | D4: 2381995
A5: Cost of Goods Sold | B5: 1337476 | C5: 1269364 | D5: 1261958
A6: Gross Profit | B6: =B4-B5 -> 1221254 | C6: =C4-C5 -> 1187727 | D6: =D4-D5 -> 1120037
A7: Selling, General and Administrative | B7: 833419 | C7: 801600 | D7: 755671
A8: Research and Development | B8: 76506 | C8: 67841 | D8: 64839
A9: Intangible Amortization | B9: 11901 | C9: 14024 | D9: 14222
A10: Income From Operations | B10: =B6-B7-B8-B9 -> 299428 | C10: =C6-C7-C8-C9 -> 304262 | D10: =D6-D7-D8-D9 -> 285305
A11: Interest Expense, Net | B11: 58288 | C11: 52637 | D11: 41288
A12: Loss on Debt Extinguishment | B12: 16970 | C12: 0 | D12: 0
A13: Other (Income) Expense, Net | B13: -15356 | C13: 1958 | D13: 2417
A14: Income Before Income Taxes | B14: =B10-B11-B12-B13 -> 239526 | C14: =C10-C11-C12-C13 -> 249667 | D14: =D10-D11-D12-D13 -> 241600
A15: Income Tax Expense | B15: 52366 | C15: 47825 | D15: 42993
A16: Net Income | B16: =B14-B15 -> 187160 | C16: =C14-C15 -> 201842 | D16: =D14-D15 -> 198607
A17: Net Loss (Income) Attributable to Noncontrolling Interests | B17: 1385 | C17: 12456 | D17: -178
A18: Net Income Attriutable to Acushnet Holdings Corp. | B18: 188545 | C18: 214298 | D18: 198429
A20: Balance Sheet
A21: Fiscal Year | B21: 2025 | C21: 2024
A22: Assets
A23: Cash, cash equivalents and restricted cash | B23: 50088 | C23: 53059
A24: Accounts Receivable, Net | B24: 217480 | C24: 218368
A25: Inventories | B25: 608571 | C25: 575964
A26: Prepaid and other assets | B26: 149232 | C26: 126482
A27: Total current assets | B27: 1025371 | C27: 973873
A28: Property, plant and equipment, net | B28: 356575 | C28: 325747
A29: Goodwill | B29: 224258 | C29: 220136
A30: Intangible assets, net | B30: 511430 | C30: 523131
A31: Deferred income taxes | B31: 21081 | C31: 34306
A32: Other assets | B32: 203984 | C32: 103013
A33: Total assets | B33: 2342699 | C33: 2180206
A34: Liabilities, Redeemable Noncontrolling Interests and Shareholders' Equity
A35: Short-term debt | B35: 16005 | C35: 10160
A36: Current portion of long-term debt | B36: 661 | C36: 722
A37: Accounts payable | B37: 156984 | C37: 150322
A38: Accrued taxes | B38: 34219 | C38: 36009
A39: Accrued compensation and benefits | B39: 100975 | C39: 95064
A40: Accrued expenses and other liabilities | B40: 121310 | C40: 180430
A41: Total current liabilities | B41: 430154 | C41: 472707
A43: Long-term debt | B43: 926244 | C43: 753081
A44: Deferred income taxes | B44: 7604 | C44: 8107
A45: Accrued pension and other postretirement benefits | B45: 68756 | C45: 74410
A46: Other noncurrent liabilites | B46: 124605 | C46: 74737
A47: Total Liabilites | B47: 1557363 | C47: 1383042
A48: Redeemable noncontrolling interests | B48: 1770 | C48: 4028
A49: Shareholders' Equity
A50: Common stock | B50: 58 | C50: 61
A51: Additional paid-in capital | B51: 763828 | C51: 787725
A52: Accumulated other comprehensive loss,net of tax | B52: -122281 | C52: -140315
A53: Retained earnings | B53: 141961 | C53: 180276
A54: Treasury stock, at cost | B54: 0 | C54: -62500
A55: Total equity attributable to Acushnet Holdings Corp. | B55: 783566 | C55: 765247
A56: Noncontrolling interests | B56: 0 | C56: 27889
A57: Total Shareholders' equity | B57: 783566 | C57: 793136
A58: Total Liabilites, Redeemable noncontrolling interests and shareholders' equity | B58: 2342699 | C58: 2180206
A60: Balance check | B60: =B33-((B47+B48+B57)) -> 0 | C60: =C33-(C47+C48+C57) -> 0
A62: Cash Flow Statements
A63: Fiscal Year | B63: 2025 | C63: 2024 | D63: 2023
A64: Cash Flows From Operating Activities
A65: Net Income | B65: 187160 | C65: 201842 | D65: 198607
A66: Depreciation and Amortization | B66: 55292 | C66: 55888 | D66: 51356
A67: Unrealized Foreign exchange (gain) loss | B67: -2823 | C67: -2856 | D67: 1507
A68: Amortization of debt issuance costs | B68: 1757 | C68: 1754 | D68: 927
A69: Share-Based compensation | B69: 28580 | C69: 30792 | D69: 29709
A70: Loss on disposals of property, plant, and equipment | B70: 725 | C70: 902 | D70: 99
A71: Gain on deconsolidation of VIE (Note 8) | B71: -20887 | C71: 0 | D71: 0
A72: Loss on equity method investment (Note 8) | B72: 1113 | C72: 0 | D72: 0
A73: Loss on debt extinguishment (Note 11) | B73: 16970 | C73: 0 | D73: 0
A74: Deffered income taxes | B74: 13941 | C74: 915 | D74: 15413
A75: Changes in operating assets and liabilities
A76: Accounts receivable | B76: 11962 | C76: -26799 | D76: 13785
A77: Inventories | B77: -20393 | C77: 21659 | D77: 58897
A78: Accounts Payable | B78: -1672 | C78: 1875 | D78: -12105
A79: Accrued Taxes | B79: -5086 | C79: -8222 | D79: 6221
A80: Other assets and liabilites | B80: -72269 | C80: -32642 | D80: 7411
A81: Cash Flow provided by operating activities | B81: 194370 | C81: 245108 | D81: 371827
A82: Cash Flows from investing activites
A83: Additions to property, plant and equipment | B83: -74342 | C83: -74624 | D83: -75364
A84: Additions to intangible assets (Note 9) | B84: 0 | C84: 0 | D84: -25235
A85: Other, Net | B85: 0 | C85: 0 | D85: -887
A86: Cash Flows used in investing activies | B86: -74342 | C86: -74624 | D86: -101486
A87: Cash Flows from financing activities
A88: Proceeds from credit facilities (Note 11) | B88: 1780933 | C88: 1243120 | D88: 1527896
A89: Repayments of credit facilities (Note 11) | B89: -1752274 | C89: -1178799 | D89: -1739308
A90: Proceeds from senior unsecured notes (Note 11) | B90: 500000 | C90: 0 | D90: 350000
A91: Repayments of senior unsexcured notes (Note 11) | B91: -350000 | C91: 0 | D91: 0
A92: Payment of redemption premium (Note 11) | B92: -12908 | C92: 0 | D92: 0
A93: Payment of debt issuance costs | B93: -9592 | C93: 0 | D93: -6328
A94: Purchases of common stock | B94: -211524 | C94: -172799 | D94: -334088
A95: Dividends paid on common stock | B95: -56156 | C95: -54291 | D95: -52480
A96: Payment of employee restricted stock tax withholding | B96: -11560 | C96: -16914 | D96: -11495
A97: Other, Net | B97: -1742 | C97: 0 | D97: 1078
A98: Cash flows used in financing activites | B98: -124823 | C98: -179683 | D98: -264725
A99: Effect of foreign exchange rates | B99: 1824 | C99: -3177 | D99: 915
... A102: End of Year | B102: 50088 | C102: 53059 | D102: 65435

Sheet Income Statement
A1: Fiscal Year | B1: 2025 | C1: 2024 | D1: 2023
A3: Income Statement
A4: Net Sales | B4: ='Raw Financials'!B4 -> 2558730 | C4: ='Raw Financials'!C4 -> 2457091 | D4: ='Raw Financials'!D4 -> 2381995
A5: Cost of Goods Sold | B5: ='Raw Financials'!B5 -> 1337476 | C5: ='Raw Financials'!C5 -> 1269364 | D5: ='Raw Financials'!D5 -> 1261958
A6: Gross Profit | B6: =B4-B5 -> 1221254 | C6: =C4-C5 -> 1187727 | D6: =D4-D5 -> 1120037
A7: Selling, General and administrative | B7: ='Raw Financials'!B7 -> 833419 | C7: ='Raw Financials'!C7 -> 801600 | D7: ='Raw Financials'!D7 -> 755671
A8: Research and Development | B8: ='Raw Financials'!B8 -> 76506 | C8: ='Raw Financials'!C8 -> 67841 | D8: ='Raw Financials'!D8 -> 64839
A9: Intangible Amortization | B9: ='Raw Financials'!B9 -> 11901 | C9: ='Raw Financials'!C9 -> 14024 | D9: ='Raw Financials'!D9 -> 14222
A10: Income from Operations | B10: =B6-B7-B8-B9 -> 299428 | C10: =C6-C7-C8-C9 -> 304262 | D10: =D6-D7-D8-D9 -> 285305
A11: Interest Expense, Net | B11: ='Raw Financials'!B11 -> 58288 | C11: ='Raw Financials'!C11 -> 52637 | D11: ='Raw Financials'!D11 -> 41288
A12: Loss on Debt Extinguishment | B12: ='Raw Financials'!B12 -> 16970 | C12: ='Raw Financials'!C12 -> 0 | D12: ='Raw Financials'!D12 -> 0
A13: Other (Income) Expense, Net | B13: ='Raw Financials'!B13 -> -15356 | C13: ='Raw Financials'!C13 -> 1958 | D13: ='Raw Financials'!D13 -> 2417
A14: Income Before Income Taxes | B14: ='Raw Financials'!B14 -> 239526 | C14: ='Raw Financials'!C14 -> 249667 | D14: ='Raw Financials'!D14 -> 241600
A15: Income Tax Expense | B15: ='Raw Financials'!B15 -> 52366 | C15: ='Raw Financials'!C15 -> 47825 | D15: ='Raw Financials'!D15 -> 42993
A16: Net Income | B16: ='Raw Financials'!B16 -> 187160 | C16: ='Raw Financials'!C16 -> 201842 | D16: ='Raw Financials'!D16 -> 198607
A17: Net Loss (Income) Attributable to Noncontrolling Interest | B17: ='Raw Financials'!B17 -> 1385 | C17: ='Raw Financials'!C17 -> 12456 | D17: ='Raw Financials'!D17 -> -178
A18: Net Income Attributable to Acushnet Holdings Corp. | B18: =B16+B17 -> 188545 | C18: =C16+C17 -> 214298 | D18: =D16+D17 -> 198429

Sheet Balance Sheet
A1: Balance Sheet
A2: Fiscal Year | B2: 2025 | C2: 2023
A3: Assets
A4: Cash, cash equivalents and restricted cash | B4: ='Raw Financials'!B23 -> 50088 | C4: ='Raw Financials'!C23 -> 53059
A5: Accounts Receivable, Net | B5: ='Raw Financials'!B24 -> 217480 | C5: ='Raw Financials'!C24 -> 218368
A6: Inventories | B6: ='Raw Financials'!B25 -> 608571 | C6: ='Raw Financials'!C25 -> 575964
A7: Prepaid and other assets | B7: ='Raw Financials'!B26 -> 149232 | C7: ='Raw Financials'!C26 -> 126482
A8: Total current assets | B8: =SUM(B4:B7) -> 1025371 | C8: =SUM(C4:C7) -> 973873
A9: Property, plant and equipment, net | B9: ='Raw Financials'!B28 -> 356575 | C9: ='Raw Financials'!C28 -> 325747
A10: Goodwill | B10: ='Raw Financials'!B29 -> 224258 | C10: ='Raw Financials'!C29 -> 220136
A11: Intangible assets, net | B11: ='Raw Financials'!B30 -> 511430 | C11: ='Raw Financials'!C30 -> 523131
A12: Deferred income taxes | B12: ='Raw Financials'!B31 -> 21081 | C12: ='Raw Financials'!C31 -> 34306
A13: Other assets | B13: ='Raw Financials'!B32 -> 203984 | C13: ='Raw Financials'!C32 -> 103013
A14: Total assets | B14: =SUM(B8:B13) -> 2342699 | C14: =SUM(C8:C13) -> 2180206
A15: Liabilities, Redeemable Noncontrolling Interests and Shareholders' Equity
A16: Short-term debt | B16: ='Raw Financials'!B35 -> 16005 | C16: ='Raw Financials'!C35 -> 10160
A17: Current portion of long-term debt | B17: ='Raw Financials'!B36 -> 661 | C17: ='Raw Financials'!C36 -> 722
A18: Accounts payable | B18: ='Raw Financials'!B37 -> 156984 | C18: ='Raw Financials'!C37 -> 150322
A19: Accrued taxes | B19: ='Raw Financials'!B38 -> 34219 | C19: ='Raw Financials'!C38 -> 36009
A20: Accrued compensation and benefits | B20: ='Raw Financials'!B39 -> 100975 | C20: ='Raw Financials'!C39 -> 95064
A21: Accrued expenses and other liabilities | B21: ='Raw Financials'!B40 -> 121310 | C21: ='Raw Financials'!C40 -> 180430
A22: Total current liabilities | B22: =SUM(B16:B21) -> 430154 | C22: =SUM(C16:C21) -> 472707
A24: Long-term debt | B24: ='Raw Financials'!B43 -> 926244 | C24: ='Raw Financials'!C43 -> 753081
A25: Deferred income taxes | B25: ='Raw Financials'!B44 -> 7604 | C25: ='Raw Financials'!C44 -> 8107
A26: Accrued pension and other postretirement benefits | B26: ='Raw Financials'!B45 -> 68756 | C26: ='Raw Financials'!C45 -> 74410
A27: Other noncurrent liabilites | B27: ='Raw Financials'!B46 -> 124605 | C27: ='Raw Financials'!C46 -> 74737
A28: Total Liabilites | B28: =SUM(B22:B27) -> 1557363 | C28: =SUM(C22:C27) -> 1383042
A30: Redeemable noncontrolling interests | B30: ='Raw Financials'!B48 -> 1770 | C30: ='Raw Financials'!C48 -> 4028
A32: Shareholders' Equity
A33: Common stock | B33: ='Raw Financials'!B50 -> 58 | C33: ='Raw Financials'!C50 -> 61
A34: Additional paid-in capital | B34: ='Raw Financials'!B51 -> 763828 | C34: ='Raw Financials'!C51 -> 787725
A35: Accumulated other comprehensive loss,net of tax | B35: ='Raw Financials'!B52 -> -122281 | C35: ='Raw Financials'!C52 -> -140315
A36: Retained earnings | B36: ='Raw Financials'!B53 -> 141961 | C36: ='Raw Financials'!C53 -> 180276
A37: Treasury stock, at cost | B37: ='Raw Financials'!B54 -> 0 | C37: ='Raw Financials'!C54 -> -62500
A38: Total equity attributable to Acushnet Holdings Corp. | B38: =SUM(B33:B37) -> 783566 | C38: =SUM(C33:C37) -> 765247
A39: Noncontrolling interests | B39: ='Raw Financials'!B56 -> 0 | C39: ='Raw Financials'!C56 -> 27889
A40: Total Shareholders' equity | B40: =B38+B39 -> 783566 | C40: =C38+C39 -> 793136
A41: Total Liabilites, Redeemable noncontrolling interests and shareholders' equity | B41: =B28+B30+B40 -> 2342699 | C41: =C28+C30+C40 -> 2180206

Sheet Cash Flow
A1: Cash Flow Statements
A2: Fiscal Year | B2: 2025 | C2: 2024 | D2: 2023
A3: Cash Flows From Operating Activities
A4: Net Income | B4: ='Raw Financials'!B65 -> 187160 | C4: ='Raw Financials'!C65 -> 201842 | D4: ='Raw Financials'!D65 -> 198607
A5: Depreciation and Amortization | B5: ='Raw Financials'!B66 -> 55292 | C5: ='Raw Financials'!C66 -> 55888 | D5: ='Raw Financials'!D66 -> 51356
A6: Unrealized Foreign exchange (gain) loss | B6: ='Raw Financials'!B67 -> -2823 | C6: ='Raw Financials'!C67 -> -2856 | D6: ='Raw Financials'!D67 -> 1507
A7: Amortization of debt issuance costs | B7: ='Raw Financials'!B68 -> 1757 | C7: ='Raw Financials'!C68 -> 1754 | D7: ='Raw Financials'!D68 -> 927
A8: Share-Based compensation | B8: ='Raw Financials'!B69 -> 28580 | C8: ='Raw Financials'!C69 -> 30792 | D8: ='Raw Financials'!D69 -> 29709
A9: Loss on disposals of property, plant, and equipment | B9: ='Raw Financials'!B70 -> 725 | C9: ='Raw Financials'!C70 -> 902 | D9: ='Raw Financials'!D70 -> 99
A10: Gain on deconsolidation of VIE (Note 8) | B10: ='Raw Financials'!B71 -> -20887 | C10: ='Raw Financials'!C71 -> 0 | D10: ='Raw Financials'!D71 -> 0
A11: Loss on equity method investment (Note 8) | B11: ='Raw Financials'!B72 -> 1113 | C11: ='Raw Financials'!C72 -> 0 | D11: ='Raw Financials'!D72 -> 0
A12: Loss on debt extinguishment (Note 11) | B12: ='Raw Financials'!B73 -> 16970 | C12: ='Raw Financials'!C73 -> 0 | D12: ='Raw Financials'!D73 -> 0
A13: Deffered income taxes | B13: ='Raw Financials'!B74 -> 13941 | C13: ='Raw Financials'!C74 -> 915 | D13: ='Raw Financials'!D74 -> 15413
A14: Changes in operating assets and liabilities
A15: Accounts receivable | B15: ='Raw Financials'!B76 -> 11962 | C15: ='Raw Financials'!C76 -> -26799 | D15: ='Raw Financials'!D76 -> 13785
A16: Inventories | B16: ='Raw Financials'!B77 -> -20393 | C16: ='Raw Financials'!C77 -> 21659 | D16: ='Raw Financials'!D77 -> 58897
A17: Accounts Payable | B17: ='Raw Financials'!B78 -> -1672 | C17: ='Raw Financials'!C78 -> 1875 | D17: ='Raw Financials'!D78 -> -12105
A18: Accrued Taxes | B18: ='Raw Financials'!B79 -> -5086 | C18: ='Raw Financials'!C79 -> -8222 | D18: ='Raw Financials'!D79 -> 6221
A19: Other assets and liabilites | B19: ='Raw Financials'!B80 -> -72269 | C19: ='Raw Financials'!C80 -> -32642 | D19: ='Raw Financials'!D80 -> 7411
A20: Cash Flow provided by operating activities | B20: =SUM(B4:B19) -> 194370 | C20: =SUM(C4:C19) -> 245108 | D20: =SUM(D4:D19) -> 371827
A21: Cash Flows from investing activites
A22: Additions to property, plant and equipment | B22: ='Raw Financials'!B83 -> -74342 | C22: ='Raw Financials'!C83 -> -74624 | D22: ='Raw Financials'!D83 -> -75364
A23: Additions to intangible assets (Note 9) | B23: ='Raw Financials'!B84 -> 0 | C23: ='Raw Financials'!C84 -> 0 | D23: ='Raw Financials'!D84 -> -25235
A24: Other, Net | B24: ='Raw Financials'!B85 -> 0 | C24: ='Raw Financials'!C85 -> 0 | D24: ='Raw Financials'!D85 -> -887
A25: Cash Flows used in investing activies | B25: =SUM(B22:B24) -> -74342 | C25: =SUM(C22:C24) -> -74624 | D25: =SUM(D22:D24) -> -101486
A26: Cash Flows from financing activities
A27: Proceeds from credit facilities (Note 11) | B27: ='Raw Financials'!B88 -> 1780933 | C27: ='Raw Financials'!C88 -> 1243120 | D27: ='Raw Financials'!D88 -> 1527896
A28: Repayments of credit facilities (Note 11) | B28: ='Raw Financials'!B89 -> -1752274 | C28: ='Raw Financials'!C89 -> -1178799 | D28: ='Raw Financials'!D89 -> -1739308
A29: Proceeds from senior unsecured notes (Note 11) | B29: ='Raw Financials'!B90 -> 500000 | C29: ='Raw Financials'!C90 -> 0 | D29: ='Raw Financials'!D90 -> 350000
A30: Repayments of senior unsexcured notes (Note 11) | B30: ='Raw Financials'!B91 -> -350000 | C30: ='Raw Financials'!C91 -> 0 | D30: ='Raw Financials'!D91 -> 0
A31: Payment of redemption premium (Note 11) | B31: ='Raw Financials'!B92 -> -12908 | C31: ='Raw Financials'!C92 -> 0 | D31: ='Raw Financials'!D92 -> 0
A32: Payment of debt issuance costs | B32: ='Raw Financials'!B93 -> -9592 | C32: ='Raw Financials'!C93 -> 0 | D32: ='Raw Financials'!D93 -> -6328
A33: Purchases of common stock | B33: ='Raw Financials'!B94 -> -211524 | C33: ='Raw Financials'!C94 -> -172799 | D33: ='Raw Financials'!D94 -> -334088
A34: Dividends paid on common stock | B34: ='Raw Financials'!B95 -> -56156 | C34: ='Raw Financials'!C95 -> -54291 | D34: ='Raw Financials'!D95 -> -52480
A35: Payment of employee restricted stock tax withholding | B35: ='Raw Financials'!B96 -> -11560 | C35: ='Raw Financials'!C96 -> -16914 | D35: ='Raw Financials'!D96 -> -11495
A36: Other, Net | B36: ='Raw Financials'!B97 -> -1742 | C36: ='Raw Financials'!C97 -> 0 | D36: ='Raw Financials'!D97 -> 1078
A37: Cash flows used in financing activites | B37: =SUM(B27:B36) -> -124823 | C37: =SUM(C27:C36) -> -179683 | D37: =SUM(D27:D36) -> -264725
A38: Effect of foreign exchange rates | B38: ='Raw Financials'!B99 -> 1824 | C38: ='Raw Financials'!C99 -> -3177 | D38: ='Raw Financials'!D99 -> 915
A39: Net (decrease) increase in cash | B39: =B20+B25+B37+B38 -> -2971 | C39: =C20+C25+C37+C38 -> -12376 | D39: =D20+D25+D37+D38 -> 6531
A40: Beginning of Year | B40: ='Raw Financials'!B101 -> 53059 | C40: ='Raw Financials'!C101 -> 65435 | D40: ='Raw Financials'!D101 -> 58904
A41: End of Year | B41: =SUM(B40+B39) -> 50088 | C41: =SUM(C40+C39) -> 53059 | D41: =SUM(D40+D39) -> 65435

Sheet Ratios & Analysis
A1: Acushnet Financial Analysis
A3: Fiscal Year | B3: 2025 | C3: 2024 | D3: 2023 | E3: 2025 vs. 2024
A5: Profitability
A6: Gross Profit Margin | B6: ='Income Statement'!B6/'Income Statement'!B4 -> 0.47728912 | C6: ='Income Statement'!C6/'Income Statement'!C4 -> 0.48338747 | D6: ='Income Statement'!D6/'Income Statement'!D4 -> 0.47020964 | E6: =B6-C6 -> -0.0060983453
A7: Operating Margin | B7: ='Income Statement'!B10/'Income Statement'!B4 -> 0.11702212 | C7: ='Income Statement'!C10/'Income Statement'!C4 -> 0.12383017 | D7: ='Income Statement'!D10/'Income Statement'!D4 -> 0.11977565 | E7: =B7-C7 -> -0.0068080551
A8: Net Profit Margin | B8: ='Income Statement'!B16/'Income Statement'!B4 -> 0.073145662 | C8: ='Income Statement'!C16/'Income Statement'!C4 -> 0.082146734 | D8: ='Income Statement'!D16/'Income Statement'!D4 -> 0.083378429 | E8: =B8-C8 -> -0.0090010716
A10: Key Observation
A11: Acushnet's Revenue increased from 2024 to 2025, while gross, operating, and net profit all declined slightly.
A13: Liquidity
A14: Current Ratio | B14: ='Balance Sheet'!B8/'Balance Sheet'!B22 -> 2.38373 | C14: ='Balance Sheet'!C8/'Balance Sheet'!C22 -> 2.0602043 | E14: =B14-C14 -> 0.3235257
A15: Quick Ratio | B15: =('Balance Sheet'!B8-'Balance Sheet'!B6)/'Balance Sheet'!B22 -> 0.9689553 | C15: =('Balance Sheet'!C8-'Balance Sheet'!C6)/'Balance Sheet'!C22 -> 0.84176668 | E15: =B15-C15 -> 0.12718863
A17: Observation
A18: Acushnet's liquidity improved in 2025, with the current ratio increasing from approximately 2.06 to 2.38 and the quick ratio increasing from approximately 0.84 to 0.97
A20: Leverage
A21: Liabilities-to-Assets Ratio | B21: ='Balance Sheet'!B28/'Balance Sheet'!B14 -> 0.66477298 | C21: ='Balance Sheet'!C28/'Balance Sheet'!C14 -> 0.63436299 | E21: =B21-C21 -> 0.030409991
A22: Liabilities-to-Equity Ratio | B22: ='Balance Sheet'!B28/'Balance Sheet'!B40 -> 1.9875326 | C22: ='Balance Sheet'!C28/'Balance Sheet'!C40 -> 1.743764 | E22: =B22-C22 -> 0.24376864
A24: Observation
A25: Acushnet's leverage increased from 2024 to 2025, with both its liabilities-to-assets and liabilities-to-equity ratios increasing
A27: Efficiancy
A28: Inventory Turnover | B28: ='Income Statement'!B5/AVERAGE('Balance Sheet'!B6,'Balance Sheet'!C6) -> 2.2582296
A29: Receivables Turnover | B29: ='Income Statement'!B4/AVERAGE('Balance Sheet'!B5,'Balance Sheet'!C5) -> 11.741387
A30: Total Asset Turnover | B30: ='Income Statement'!B4/AVERAGE('Balance Sheet'!B14,'Balance Sheet'!C14) -> 1.1314542
A32: Observation
A33: Acushnet generated $1.13 in sales for every $1.00 of average assets in 2025. Receivables turnover was relatively strong at 11.75x, while inventory turned over 2.26x during the year.
A35: Return Ratios
A36: Return on Assets (ROA) | B36: ='Income Statement'!B16/AVERAGE('Balance Sheet'!B14,'Balance Sheet'!C14) -> 0.082760969
A37: Return on Equity (ROE) | B37: ='Income Statement'!B18/AVERAGE('Balance Sheet'!B38,'Balance Sheet'!C38) -> 0.24347032
A39: Observation
A40: Acushnet generated and 8.28% return on its average assets and a 24.35% return on average equity in 2025. The higher ROE indicates that the company generated a substantially stronger return for shareholders than its overall return on assets.
A42: Cash Flow Analysis
A43: Operating Cash Flow Margin | B43: ='Cash Flow'!B20/'Income Statement'!B4 -> 0.075963466
A44: Free Cash Flow | B44: ='Cash Flow'!B20+'Cash Flow'!B22 -> 120028
A45: Free Cash Flow Margin | B45: =B44/'Income Statement'!B4 -> 0.046909209
A47: Observation
A48: Acushnet generated $194.4 Million of operating cash flow and $120.0 million of free cash flow in 2025. Free cash flow represented 4.69% of net sales after capital expenditures.
A50: Overall Financial Analysis
A51: Profitability
A52: Acushnet's sales increased from 2024 to 2025, but profitability margin decreased from 48.34% to 47.73%, operating margin declined from 12.38% to 11.70%, and net profit margin declined from 8.21% to 7.32%. This indicates that Acushnnet generated more sales but retained slightly less profit from those sales.
A54: Liquidity
A55: Acushnet's liquidity improved in 2025. The current ratio increased from 2.06 to 2.38, while the quick ratio increased from 0.84 to 0.97. This suggests the company had a stronger ability to meet its short-term obligations, although quick assets remained slightly below current liabilites
A57: Leverage
A58: Acushnet's leverage increased in 2025. Liabilities-to-assets increased from 63.44% to 66.48%, while liabilities-to-equity increased from 1.74x to 1.99x. This indicates that a greater portion of the company's assets was financed through liabilities, increasing financial leverage
A60: Efficiency
A61: In 2025, Acushnet generated 11.75x receivables turnover, 2.26x inventory turnover, and 1.13x total asset turnover. These measures provide insight into how effectively the company converted its receivables, inventory, and asset base into sales.
A63: Returns
... A67: Acushnet generated $194.4 million. In operating cash flow and $120.0 million in free cash flow during 2025. Operating cash flow represented 7.60% of sales, while free cash flow represented 4.69% of sales after capital expenditures

Sheet Dashboard
A1: Acushnet Holdings Corp.
A2: 2025 Financial Statement and Ratio Analysis
A3: Based on 2025 Form 10-K | Excel Financial Analysis Project
A5: Key Financial Metrics | D5: Liquidity & Leverage
A6: Net Sales | B6: ='Income Statement'!B4 -> 2558730 | D6: Current Ratio | E6: ='Ratios & Analysis'!B14 -> 2.38373
A7: Net Income | B7: ='Income Statement'!B16 -> 187160 | D7: Quick Ratio | E7: ='Ratios & Analysis'!B15 -> 0.9689553
A8: Gross Profit Margin | B8: ='Ratios & Analysis'!B6 -> 0.47728912 | D8: Liabilities-to-Assets | E8: ='Ratios & Analysis'!B21 -> 0.66477298
A9: Operating Margin | B9: ='Ratios & Analysis'!B7 -> 0.11702212 | D9: Liabilities-to-Equity | E9: ='Ratios & Analysis'!B22 -> 1.9875326
A10: Net Profit Margin | B10: ='Ratios & Analysis'!B8 -> 0.073145662
A13: Efficiency & Returns | D13: Cash Flow
A14: Inventory Turnover | B14: ='Ratios & Analysis'!B28 -> 2.2582296 | D14: Operating Cash Flow | E14: ='Cash Flow'!B20 -> 194370
A15: Receivables Turnover | B15: ='Ratios & Analysis'!B29 -> 11.741387 | D15: Free Cash Flow | E15: ='Ratios & Analysis'!B44 -> 120028
A16: Total Asset Turnover | B16: ='Ratios & Analysis'!B30 -> 1.1314542 | D16: Operating Cash Flow Margin | E16: ='Ratios & Analysis'!B43 -> 0.075963466
A17: Return on Assets | B17: ='Ratios & Analysis'!B36 -> 0.082760969 | D17: Free Cash Flow Margin | E17: ='Ratios & Analysis'!B45 -> 0.046909209
A18: Return on Equity | B18: ='Ratios & Analysis'!B37 -> 0.24347032
A21: 2024 -> 2025 Key Trends | B21: 2024 | C21: 2025 | D21: Key Findings
A22: Net Sales | B22: ='Income Statement'!C4 -> 2457091 | C22: ='Income Statement'!B4 -> 2558730 | D22: Sales increased, but profitability margins declined
A23: Gross Profit Margin | B23: ='Ratios & Analysis'!C6 -> 0.48338747 | C23: ='Ratios & Analysis'!B6 -> 0.47728912 | D23: liquidity improved while leverage increased
A24: Operating Margin | B24: ='Ratios & Analysis'!C7 -> 0.12383017 | C24: ='Ratios & Analysis'!B7 -> 0.11702212 | D24: Operating Cash Flow and Free Cash Flow remained positive in 2025
A25: Net Profit Margin | B25: ='Ratios & Analysis'!C8 -> 0.082146734 | C25: ='Ratios & Analysis'!B8 -> 0.073145662
A26: Current Ratio | B26: ='Ratios & Analysis'!C14 -> 2.0602043 | C26: ='Ratios & Analysis'!B14 -> 2.38373 | D26: 2025 Highlights
A27: Liabilities-to-Assets | B27: ='Ratios & Analysis'!C21 -> 0.63436299 | C27: ='Ratios & Analysis'!B21 -> 0.66477298 | D27: Net Sales: $2.56B
D28: Operating Cash Flow: $194.4M
D29: Free Cash Flow: $120.0M
D30: ROE: 24.35%
